{
  "id": "po-zhen-zi__people__zheng-hongkui",
  "title": "郑鸿逵 / Zheng Hongkui",
  "sourcePath": "references/southern-ming/people/zheng-hongkui.md",
  "html": "<blockquote><p>Stable draft ID: <code>person.zheng_hongkui</code><br />Status: anchored seed profile</p></blockquote>\n<h3>身份</h3>\n<p>郑鸿逵，郑芝龙之弟，弘光、隆武之际的福建和海上将领。弘光时参与江防，南京覆亡后奉唐王朱聿键入闽，是隆武继统的重要拥立者之一。</p>\n<h3>生平和主要事迹</h3>\n<ul><li>弘光朝廷时期，郑鸿逵在长江下游江防、水师和福建郑氏军事网络中活动；CText《臺灣鄭氏始末》卷一记其封靖虏伯、守镇江，并在弘光末局以水师守瓜洲。</li><li>1645 年扬州失守后到南京迎降前，《南明史稿》《明季南略》等本地旧籍把郑鸿逵放在京口至海门、镇江/京口和防江水师位置；清军自瓜洲渡江后，材料记郑鸿逵入海/走福建，蒋云台降清，镇江遂陷。此层只证明郑鸿逵处在江防失位和退走窗口，不定案兵船数量、战术路线或个人责任比例。</li><li>南京失守后，郑鸿逵、郑彩等退回福建方向，途中奉朱聿键至福州，参与隆武继统；卷一和本地《海上见闻录》《明季南略》均可把退闽水师和隆武建政桥接起来。</li><li>隆武政权建立后，郑鸿逵受封并被纳入郑氏军政集团的高位结构，卷一又把郑芝龙与黄道周朝班冲突、何楷呵责郑鸿逵等放在郑氏宿将不平背景中。</li><li>隆武要求郑氏兵出关时，《明季南略》记郑鸿逵名义上出浙东；顾诚材料则记其部将黄克辉从浙江江山撤回闽，隆武因而降郑鸿逵少师。CText《臺灣鄭氏始末》卷一另记郑鸿逵自浙还浦城，并因郑彩奉鲁王入闽而受连带削爵。</li><li>郑芝龙降清并被挟北上后，郑鸿逵没有随郑芝龙北去，而是与郑成功等继续入海抗清；卷一所载劝兄勿赴清营属整理本政治话语，需与郑氏原书和清方材料互校。</li><li>CText《臺灣鄭氏始末》卷二记郑成功令郑鸿逵镇金门，后又在泉州桃花山与郑鸿逵会师攻泉州；《閩海紀要》《海上見聞錄》也可互校 1647 年郑成功会郑鸿逵攻泉州、赵国祚桃花山败绩和漳州援兵解围的主线。同卷后段还把厦门失守后郑成功与郑鸿逵生隙放在思明州整合背景中。</li><li>《海上見聞錄》在 1649-1651 年线索中又见郑成功于揭阳会郑鸿逵、郑鸿逵回厦门、张学圣/马得功袭厦门后郑鸿逵截港围攻和退泊白沙等节点；这可补其在潮州线和厦门失守后的中间支系位置。</li><li>《閩海紀要》记 1657 年春三月郑鸿逵卒于金门，郑成功闻讯回思明州；年龄、卒日和晚年居处仍需继续校。</li></ul>\n<h3>性格、评价和行为模式提取</h3>\n<ul><li>行为模式：宗族型海上将领，既参与宗藩拥立，也依托郑氏家族舰队和海上基地行动。</li><li>与郑芝龙相比，郑鸿逵在隆武覆灭后的选择更接近“保持海上独立与抗清旗号”，但具体战略自主性需再细分。</li><li>对建模有用的是“中间支系”：既不是郑芝龙降清线，也不是郑成功后期主导线，却能解释郑氏集团如何在 1646-1647 年分裂重组。</li><li>卷二补强其在早期金门、泉州和厦门整合中的支系节点位置，但责任和动机仍不能只凭整理本定案。</li></ul>\n<h3>著作或文本</h3>\n<ul><li>未见个人著作；相关材料主要散见于编年、郑氏海上资料和地方志。</li></ul>\n<h3>游戏数据线索</h3>\n<ul><li><code>Faction Bridge</code>: 郑氏家族内部从福建官军、隆武拥立到海上抗清的桥接人物。</li><li><code>RiverDefenseCommandNode</code> / <code>FleetNonEngagementRisk</code>: 弘光五月镇江/瓜洲江防失位和水师退走节点。</li><li><code>MaritimeFactionExit</code>: 南京覆亡窗口中从长江江防退往福建/海上的分流。</li><li><code>Historical Candidate</code>: 若郑鸿逵能更早整合海上支系，郑成功早期动员可能有不同速度。</li><li><code>Relation Memory</code>: 与郑芝龙、郑成功、郑彩、鲁监国之间的关系需要在后续人物网络中细化。</li></ul>\n<h3>来源</h3>\n<ul><li>已核锚点：<code>../source-audit.md#audit-sm-0047</code>，<code>../source-audit.md#audit-sm-0050</code>，<code>../source-audit.md#audit-sm-0071</code>，<code>../source-audit.md#audit-sm-0074</code>。</li><li>CText《臺灣鄭氏始末》卷一锚点：<code>../source-audit.md#audit-sm-0339</code>，<code>../source-audit.md#audit-sm-0340</code>，<code>../source-audit.md#audit-sm-0341</code>，<code>../source-audit.md#audit-sm-0342</code>。</li><li>CText《臺灣鄭氏始末》卷二锚点：<code>../source-audit.md#audit-sm-0335</code>，<code>../source-audit.md#audit-sm-0337</code>。</li><li>本地《閩海紀要》《海上見聞錄》早期起兵、厦门整合和卒年锚点：<code>../source-audit.md#audit-sm-0343</code>，<code>../source-audit.md#audit-sm-0345</code>，<code>../source-audit.md#audit-sm-0347</code>，<code>../source-audit.md#audit-sm-0348</code>，<code>../source-audit.md#audit-sm-0359</code>。</li><li>镇江/瓜洲江防失位锚点：<code>../source-audit.md#audit-sm-0516</code>；source-note <code>data/era-packages/southern-ming/source-notes/hongguang-zhenjiang-guazhou-river-defense-collapse-1645.json</code>。</li><li>顾诚：《南明史》，隆武和郑氏相关章节，<code>references/southern-ming/books/gu-cheng-nanming-shi-guangming-2011.epub</code>。</li><li>Wikisource《明季南略》《海上見聞錄》《閩海紀要》，<code>references/southern-ming/primary-sources/wikisource/</code>。</li></ul>\n<h3>待辨析</h3>\n<ul><li>郑鸿逵在弘光镇江/瓜洲江防失败中的具体责任、兵力、战船数、退走路线和南京命令关系。</li><li>隆武时期郑鸿逵与郑芝龙在出关、军饷和朝廷关系上的分工。</li><li>郑鸿逵因郑彩奉鲁王入闽而受累削爵的日序、责任逻辑和卷一叙述源流需继续校。</li><li>1647 年以后郑鸿逵、郑成功、郑彩、郑联之间的舰队和基地分合，以及厦门失守后郑成功与郑鸿逵关系裂痕。</li><li>1657 年卒于金门的日级日期、年齿和葬祭线索需地方志、郑氏原书和墓志/谱牒校。</li></ul>",
  "plainText": "郑鸿逵 / Zheng Hongkui Stable draft ID: person.zheng hongkui Status: anchored seed profile 身份 郑鸿逵，郑芝龙之弟，弘光、隆武之际的福建和海上将领。弘光时参与江防，南京覆亡后奉唐王朱聿键入闽，是隆武继统的重要拥立者之一。 生平和主要事迹 弘光朝廷时期，郑鸿逵在长江下游江防、水师和福建郑氏军事网络中活动；CText《臺灣鄭氏始末》卷一记其封靖虏伯、守镇江，并在弘光末局以水师守瓜洲。 1645 年扬州失守后到南京迎降前，《南明史稿》《明季南略》等本地旧籍把郑鸿逵放在京口至海门、镇江/京口和防江水师位置；清军自瓜洲渡江后，材料记郑鸿逵入海/走福建，蒋云台降清，镇江遂陷。此层只证明郑鸿逵处在江防失位和退走窗口，不定案兵船数量、战术路线或个人责任比例。 南京失守后，郑鸿逵、郑彩等退回福建方向，途中奉朱聿键至福州，参与隆武继统；卷一和本地《海上见闻录》《明季南略》均可把退闽水师和隆武建政桥接起来。 隆武政权建立后，郑鸿逵受封并被纳入郑氏军政集团的高位结构，卷一又把郑芝龙与黄道周朝班冲突、何楷呵责郑鸿逵等放在郑氏宿将不平背景中。 隆武要求郑氏兵出关时，《明季南略》记郑鸿逵名义上出浙东；顾诚材料则记其部将黄克辉从浙江江山撤回闽，隆武因而降郑鸿逵少师。CText《臺灣鄭氏始末》卷一另记郑鸿逵自浙还浦城，并因郑彩奉鲁王入闽而受连带削爵。 郑芝龙降清并被挟北上后，郑鸿逵没有随郑芝龙北去，而是与郑成功等继续入海抗清；卷一所载劝兄勿赴清营属整理本政治话语，需与郑氏原书和清方材料互校。 CText《臺灣鄭氏始末》卷二记郑成功令郑鸿逵镇金门，后又在泉州桃花山与郑鸿逵会师攻泉州；《閩海紀要》《海上見聞錄》也可互校 1647 年郑成功会郑鸿逵攻泉州、赵国祚桃花山败绩和漳州援兵解围的主线。同卷后段还把厦门失守后郑成功与郑鸿逵生隙放在思明州整合背景中。 《海上見聞錄》在 1649 1651 年线索中又见郑成功于揭阳会郑鸿逵、郑鸿逵回厦门、张学圣/马得功袭厦门后郑鸿逵截港围攻和退泊白沙等节点；这可补其在潮州线和厦门失守后的中间支系位置。 《閩海紀要》记 1657 年春三月郑鸿逵卒于金门，郑成功闻讯回思明州；年龄、卒日和晚年居处仍需继续校。 性格、评价和行为模式提取 行为模式：宗族型海上将领，既参与宗藩拥立，也依托郑氏家族舰队和海上基地行动。 与郑芝龙相比，郑鸿逵在隆武覆灭后的选择更接近“保持海上独立与抗清旗号”，但具体战略自主性需再细分。 对建模有用的是“中间支系”：既不是郑芝龙降清线，也不是郑成功后期主导线，却能解释郑氏集团如何在 1646 1647 年分裂重组。 卷二补强其在早期金门、泉州和厦门整合中的支系节点位置，但责任和动机仍不能只凭整理本定案。 著作或文本 未见个人著作；相关材料主要散见于编年、郑氏海上资料和地方志。 游戏数据线索 Faction Bridge: 郑氏家族内部从福建官军、隆武拥立到海上抗清的桥接人物。 RiverDefenseCommandNode / FleetNonEngagementRisk: 弘光五月镇江/瓜洲江防失位和水师退走节点。 MaritimeFactionExit: 南京覆亡窗口中从长江江防退往福建/海上的分流。 Historical Candidate: 若郑鸿逵能更早整合海上支系，郑成功早期动员可能有不同速度。 Relation Memory: 与郑芝龙、郑成功、郑彩、鲁监国之间的关系需要在后续人物网络中细化。 来源 已核锚点：../source audit.md audit sm 0047，../source audit.md audit sm 0050，../source audit.md audit sm 0071，../source audit.md audit sm 0074。 CText《臺灣鄭氏始末》卷一锚点：../source audit.md audit sm 0339，../source audit.md audit sm 0340，../source audit.md audit sm 0341，../source audit.md audit sm 0342。 CText《臺灣鄭氏始末》卷二锚点：../source audit.md audit sm 0335，../source audit.md audit sm 0337。 本地《閩海紀要》《海上見聞錄》早期起兵、厦门整合和卒年锚点：../source audit.md audit sm 0343，../source audit.md audit sm 0345，../source audit.md audit sm 0347，../source audit.md audit sm 0348，../source audit.md audit sm 0359。 镇江/瓜洲江防失位锚点：../source audit.md audit sm 0516；source note data/era packages/southern ming/source notes/hongguang zhenjiang guazhou river defense collapse 1645.json。 顾诚：《南明史》，隆武和郑氏相关章节，references/southern ming/books/gu cheng nanming shi guangming 2011.epub。 Wikisource《明季南略》《海上見聞錄》《閩海紀要》，references/southern ming/primary sources/wikisource/。 待辨析 郑鸿逵在弘光镇江/瓜洲江防失败中的具体责任、兵力、战船数、退走路线和南京命令关系。 隆武时期郑鸿逵与郑芝龙在出关、军饷和朝廷关系上的分工。 郑鸿逵因郑彩奉鲁王入闽而受累削爵的日序、责任逻辑和卷一叙述源流需继续校。 1647 年以后郑鸿逵、郑成功、郑彩、郑联之间的舰队和基地分合，以及厦门失守后郑成功与郑鸿逵关系裂痕。 1657 年卒于金门的日级日期、年齿和葬祭线索需地方志、郑氏原书和墓志/谱牒校。"
}
