{
  "id": "po-zhen-zi__people__wang-shijie-taihe",
  "title": "王士杰（太和） / Wang Shijie, Taihe",
  "sourcePath": "references/southern-ming/people/wang-shijie-taihe/profile.md",
  "portrait": {
    "imagePath": "/wiki-content/po-zhen-zi/people/wang-shijie-taihe/portrait.png",
    "caption": "AI generated game concept art, style inspired from local text; the likeness is not authenticated",
    "alt": "王士杰（太和） / Wang Shijie, Taihe portrait concept art",
    "sourcePath": "references/southern-ming/people/wang-shijie-taihe/portrait.md"
  },
  "html": "<blockquote><p>Stable draft ID: <code>person.wang_shijie_taihe</code><br />Status: anchored seed profile; identity pending.</p></blockquote>\n<h3>身份</h3>\n<p>王士杰，维基文库《明史》卷二百九十五所见太和县丞。</p>\n<h3>生平和主要事迹</h3>\n<ul><li>《明史》卷二百九十五记沙定洲部进围大理时，太和县丞王士杰协助上官守御，城陷后死于城上。</li><li>本地 CBDB 20260530 有多条 <code>王士傑</code> 同名记录，其中 <code>c_personid=126446</code> 仅作弱候选，未见足以证明太和县丞/大理死事的任官或地址字段。</li><li>该页为未校对公开文本；太和县、官职和死亡细节需点校本、大理府志和太和地方材料复核。</li></ul>\n<h3>性格、评价和行为模式提取</h3>\n<ul><li>行为模式：县佐官参与府城/地方城防的死事记忆层。</li><li>不从单一来源抽取性格。</li></ul>\n<h3>著作或文本</h3>\n<ul><li>未见。</li></ul>\n<h3>游戏数据线索</h3>\n<ul><li><code>Event Participant</code>: 大理/太和守御。</li><li><code>Local Office</code>: 太和县丞。</li></ul>\n<h3>来源</h3>\n<ul><li><code>../source-audit.md#audit-sm-0422</code>：维基文库《明史》卷二百九十五所见楚雄、武定和大理人物层。</li><li><code>../source-audit.md#audit-sm-0427</code>：本地 CBDB 所见王士杰同名风险。</li></ul>\n<h3>待辨析</h3>\n<ul><li>王士杰任职、城防所属地点、与大理陷落日序的关系和 CBDB 同名记录待校；暂不挂稳定 externalRefs。</li></ul>",
  "plainText": "王士杰（太和） / Wang Shijie, Taihe Stable draft ID: person.wang shijie taihe Status: anchored seed profile; identity pending. 身份 王士杰，维基文库《明史》卷二百九十五所见太和县丞。 生平和主要事迹 《明史》卷二百九十五记沙定洲部进围大理时，太和县丞王士杰协助上官守御，城陷后死于城上。 本地 CBDB 20260530 有多条 王士傑 同名记录，其中 c personid=126446 仅作弱候选，未见足以证明太和县丞/大理死事的任官或地址字段。 该页为未校对公开文本；太和县、官职和死亡细节需点校本、大理府志和太和地方材料复核。 性格、评价和行为模式提取 行为模式：县佐官参与府城/地方城防的死事记忆层。 不从单一来源抽取性格。 著作或文本 未见。 游戏数据线索 Event Participant: 大理/太和守御。 Local Office: 太和县丞。 来源 ../source audit.md audit sm 0422：维基文库《明史》卷二百九十五所见楚雄、武定和大理人物层。 ../source audit.md audit sm 0427：本地 CBDB 所见王士杰同名风险。 待辨析 王士杰任职、城防所属地点、与大理陷落日序的关系和 CBDB 同名记录待校；暂不挂稳定 externalRefs。"
}
