{
  "id": "po-zhen-zi__people__gong-yi",
  "title": "龚彝 / Gong Yi",
  "sourcePath": "references/southern-ming/people/gong-yi.md",
  "html": "<blockquote><p>Stable draft ID: <code>person.gong_yi</code><br />Status: anchored seed profile</p></blockquote>\n<h3>身份</h3>\n<p>龚彝，永历后期旧臣。《小腆紀年》在 1662 年永历押回云南后称其为明前户部尚书，并注明其为孙可望私人。</p>\n<h3>生平和主要事迹</h3>\n<ul><li>《小腆紀年》在杨畏知遇害线索中记龚彝等曾主张加赋，处于孙可望国主化和财政压力叙述中。</li><li>1662 年永历被押回云南后，《小腆紀年》记龚彝携酒肴进谒，称君臣之义南北皆同；入见后行朝礼、进酒，永历痛哭不能饮，龚彝拜哭至触地而死。</li></ul>\n<h3>性格、评价和行为模式提取</h3>\n<ul><li>当前只能提取为：在孙可望体系中有旧关系，又在永历终局表现出君臣礼义的复杂旧臣节点。</li><li>不宜据单条死节叙述直接反推其早年政治品格或完整忠逆评价。</li></ul>\n<h3>著作或文本</h3>\n<ul><li>未见。</li></ul>\n<h3>游戏数据线索</h3>\n<ul><li><code>Memory Layer</code>: 永历押回昆明后的旧臣进谒和礼义记忆。</li><li><code>Character Ambiguity</code>: 孙可望私人、前户部尚书与终局死节之间的评价张力。</li></ul>\n<h3>相关事件</h3>\n<ul><li><code>../events/yongli-burma-terminal-network-1659-1662.md</code>：终局中龚彝进谒和昆明尾声记忆层的总入口。</li><li><code>../events/yongli-execution-1662.md</code>：永历帝死亡。</li></ul>\n<h3>来源</h3>\n<ul><li>已核锚点：<code>../source-audit.md#audit-sm-0287</code>，<code>../source-audit.md#audit-sm-0311</code>。</li></ul>\n<h3>待辨析</h3>\n<ul><li>1650s 国主化线索中的龚彝与 1662 前户部尚书龚彝是否完全同一人，官职履历、与孙可望关系和死亡细节需继续校。</li></ul>",
  "plainText": "龚彝 / Gong Yi Stable draft ID: person.gong yi Status: anchored seed profile 身份 龚彝，永历后期旧臣。《小腆紀年》在 1662 年永历押回云南后称其为明前户部尚书，并注明其为孙可望私人。 生平和主要事迹 《小腆紀年》在杨畏知遇害线索中记龚彝等曾主张加赋，处于孙可望国主化和财政压力叙述中。 1662 年永历被押回云南后，《小腆紀年》记龚彝携酒肴进谒，称君臣之义南北皆同；入见后行朝礼、进酒，永历痛哭不能饮，龚彝拜哭至触地而死。 性格、评价和行为模式提取 当前只能提取为：在孙可望体系中有旧关系，又在永历终局表现出君臣礼义的复杂旧臣节点。 不宜据单条死节叙述直接反推其早年政治品格或完整忠逆评价。 著作或文本 未见。 游戏数据线索 Memory Layer: 永历押回昆明后的旧臣进谒和礼义记忆。 Character Ambiguity: 孙可望私人、前户部尚书与终局死节之间的评价张力。 相关事件 ../events/yongli burma terminal network 1659 1662.md：终局中龚彝进谒和昆明尾声记忆层的总入口。 ../events/yongli execution 1662.md：永历帝死亡。 来源 已核锚点：../source audit.md audit sm 0287，../source audit.md audit sm 0311。 待辨析 1650s 国主化线索中的龚彝与 1662 前户部尚书龚彝是否完全同一人，官职履历、与孙可望关系和死亡细节需继续校。"
}
