{
  "id": "po-zhen-zi__people__zhu-youlang",
  "title": "朱由榔 / 永历帝",
  "sourcePath": "references/southern-ming/people/zhu-youlang/profile.md",
  "portrait": {
    "imagePath": "/wiki-content/po-zhen-zi/people/zhu-youlang/portrait.png",
    "caption": "AI generated game concept art from local profile text only; not an authenticated likeness or evidence source.",
    "alt": "朱由榔 / 永历帝 portrait concept art",
    "sourcePath": "references/southern-ming/people/zhu-youlang/portrait.md"
  },
  "html": "<blockquote><p>Stable draft ID: <code>person.zhu_youlang</code><br />Status: seed profile</p></blockquote>\n<h3>身份</h3>\n<p>朱由榔，桂王，后为永历帝。南明后期名义上的核心皇帝，活动范围从两广、云贵延伸到缅甸。</p>\n<h3>生平和主要事迹</h3>\n<ul><li>1646 年在肇庆监国并继统；赣州失守后曾出奔梧州，随后因广州绍武并立而返回肇庆称帝，次年改元永历；广州陷落后又转入西走流亡。</li><li>1648 年李成栋广东反正后，由南宁东返肇庆，短暂重返两广政治中心。</li><li>1649 年南昌、湘潭、信丰相继失利后，永历朝廷再次陷入惊惶和军政集团失控。</li><li>1650 年广州、桂林相继失守后，由梧州、浔州逃入南宁；陈邦傅叛降、焦琏遇害使广西根基进一步崩裂。</li><li>1651 年南宁失守后，经左江和滇桂边界逃亡，1652 年初被孙可望迎入安龙。</li><li>长期依赖西南军事集团，先后受到丁魁楚、瞿式耜、孙可望、李定国、马吉翔等人物和集团制约。</li><li>1654 年在安龙受孙可望控制，朝臣秘密联络李定国救驾，密诏事发后形成“十八先生案”。</li><li>1655-1656 年在白文选拖延和李定国迎驾后离开安龙，经曲靖至昆明，并重新封授李定国、刘文秀等。</li><li>1657 年孙可望内犯云南失败并降清后，永历朝廷虽暂离孙可望直接控制，却面对清方掌握西南情报的新危机。</li><li>1658 年清军三路入滇，永历朝廷讨论西撤，入缅前夜到来。</li><li>1659 年在清军西南攻势后进入缅甸；入境前后随行人员解除武装，护卫失序，入缅后又被安置在阿瓦附近，通信和会见均受缅方与近臣过滤。</li><li>1661 年咒水之难后，随行朝廷几乎瓦解，永历本人从流亡皇帝进一步变成缅方控制下、清方索取中的人质。</li><li>1661 年十二月被缅方交出，王会/高得捷等接收链条有异文；1662 年被押回昆明后处死，四月十五/四月二十五和故都督府/李本高宅/小庙/篦子坡等地点叙述仍需辨析。押回昆明后，《小腆紀年》又记龚彝进谒并拜哭触地而死，属于终局礼义记忆层。</li></ul>\n<h3>性格、评价和行为模式提取</h3>\n<ul><li>资料多呈现其柔弱、受制于权臣/军阀、难以主动整合资源的一面。</li><li>游戏行为模式可抽取为：合法性象征很强，个人决断和军事控制弱，容易被护驾集团、近臣过滤层、宿主国王权和清方军事压力共同操控；在流亡中不断损失行动渠道。</li><li>关键建模点：永历本人常是各集团争夺的合法性中枢，其移动会改变军政联盟、封授秩序、补给方向和清方追击目标。</li></ul>\n<h3>著作或文本</h3>\n<ul><li>永历诏令、敕札、行在文书待补。</li></ul>\n<h3>游戏数据线索</h3>\n<ul><li><code>Authority</code>: 永历朝廷。</li><li><code>Continuity Anchor</code>: 明朔、皇帝本人、流亡行在。</li><li><code>Historical Candidate</code>: 安龙密诏、永历迁昆明、清军西南总攻、入缅、咒水之难、被引渡、处死。</li><li><code>Player Seat</code>: 低行动力高象征性君主位。</li></ul>\n<h3>相关事件</h3>\n<ul><li><code>../events/yongli-burma-terminal-network-1659-1662.md</code>：入缅、咒水、逼缅、押回昆明和死亡的终局总入口。</li><li><code>../events/yongli-flight-to-burma-1659.md</code>：永历入缅。</li><li><code>../events/yongli-execution-1662.md</code>：永历帝死亡。</li></ul>\n<h3>来源</h3>\n<ul><li>已核锚点：<code>../source-audit.md#audit-sm-0005</code>，<code>../source-audit.md#audit-sm-0008</code>，<code>../source-audit.md#audit-sm-0009</code>，<code>../source-audit.md#audit-sm-0010</code>，<code>../source-audit.md#audit-sm-0024</code>，<code>../source-audit.md#audit-sm-0025</code>，<code>../source-audit.md#audit-sm-0027</code>，<code>../source-audit.md#audit-sm-0028</code>，<code>../source-audit.md#audit-sm-0054</code>，<code>../source-audit.md#audit-sm-0056</code>，<code>../source-audit.md#audit-sm-0082</code>，<code>../source-audit.md#audit-sm-0083</code>，<code>../source-audit.md#audit-sm-0084</code>，<code>../source-audit.md#audit-sm-0089</code>，<code>../source-audit.md#audit-sm-0090</code>，<code>../source-audit.md#audit-sm-0091</code>，<code>../source-audit.md#audit-sm-0093</code>，<code>../source-audit.md#audit-sm-0149</code>，<code>../source-audit.md#audit-sm-0154</code>，<code>../source-audit.md#audit-sm-0259</code>，<code>../source-audit.md#audit-sm-0260</code>，<code>../source-audit.md#audit-sm-0261</code>，<code>../source-audit.md#audit-sm-0262</code>，<code>../source-audit.md#audit-sm-0264</code>，<code>../source-audit.md#audit-sm-0265</code>，<code>../source-audit.md#audit-sm-0311</code>，<code>../source-audit.md#audit-sm-0312</code>。</li><li>顾诚：《南明史》，永历、西南、入缅、咒水之难和被杀相关章节，<code>references/southern-ming/books/gu-cheng-nanming-shi-guangming-2011.epub</code>。</li><li>Wikisource《小腆纪年》《明季南略》，<code>references/southern-ming/primary-sources/wikisource/</code>。</li></ul>\n<h3>待辨析</h3>\n<ul><li>永历具体决策责任与马吉翔、李国泰、孙可望等人的责任边界。</li><li>1646 肇庆监国、梧州出奔、广州绍武并立和肇庆称帝的日级顺序需继续校。</li><li>1654 安龙密诏、1656 迁昆明、1658 西撤讨论中永历本人意志与朝臣/将领推动的边界需逐源辨析。</li><li>1651 南宁失守日、左江至安龙路线和安龙控制结构需继续地理/制度校勘。</li><li>入缅后敕书、玉玺、征南将军印核验和清方接收永历日序，需缅甸资料、清方资料和地方志继续互证。</li></ul>",
  "plainText": "朱由榔 / 永历帝 Stable draft ID: person.zhu youlang Status: seed profile 身份 朱由榔，桂王，后为永历帝。南明后期名义上的核心皇帝，活动范围从两广、云贵延伸到缅甸。 生平和主要事迹 1646 年在肇庆监国并继统；赣州失守后曾出奔梧州，随后因广州绍武并立而返回肇庆称帝，次年改元永历；广州陷落后又转入西走流亡。 1648 年李成栋广东反正后，由南宁东返肇庆，短暂重返两广政治中心。 1649 年南昌、湘潭、信丰相继失利后，永历朝廷再次陷入惊惶和军政集团失控。 1650 年广州、桂林相继失守后，由梧州、浔州逃入南宁；陈邦傅叛降、焦琏遇害使广西根基进一步崩裂。 1651 年南宁失守后，经左江和滇桂边界逃亡，1652 年初被孙可望迎入安龙。 长期依赖西南军事集团，先后受到丁魁楚、瞿式耜、孙可望、李定国、马吉翔等人物和集团制约。 1654 年在安龙受孙可望控制，朝臣秘密联络李定国救驾，密诏事发后形成“十八先生案”。 1655 1656 年在白文选拖延和李定国迎驾后离开安龙，经曲靖至昆明，并重新封授李定国、刘文秀等。 1657 年孙可望内犯云南失败并降清后，永历朝廷虽暂离孙可望直接控制，却面对清方掌握西南情报的新危机。 1658 年清军三路入滇，永历朝廷讨论西撤，入缅前夜到来。 1659 年在清军西南攻势后进入缅甸；入境前后随行人员解除武装，护卫失序，入缅后又被安置在阿瓦附近，通信和会见均受缅方与近臣过滤。 1661 年咒水之难后，随行朝廷几乎瓦解，永历本人从流亡皇帝进一步变成缅方控制下、清方索取中的人质。 1661 年十二月被缅方交出，王会/高得捷等接收链条有异文；1662 年被押回昆明后处死，四月十五/四月二十五和故都督府/李本高宅/小庙/篦子坡等地点叙述仍需辨析。押回昆明后，《小腆紀年》又记龚彝进谒并拜哭触地而死，属于终局礼义记忆层。 性格、评价和行为模式提取 资料多呈现其柔弱、受制于权臣/军阀、难以主动整合资源的一面。 游戏行为模式可抽取为：合法性象征很强，个人决断和军事控制弱，容易被护驾集团、近臣过滤层、宿主国王权和清方军事压力共同操控；在流亡中不断损失行动渠道。 关键建模点：永历本人常是各集团争夺的合法性中枢，其移动会改变军政联盟、封授秩序、补给方向和清方追击目标。 著作或文本 永历诏令、敕札、行在文书待补。 游戏数据线索 Authority: 永历朝廷。 Continuity Anchor: 明朔、皇帝本人、流亡行在。 Historical Candidate: 安龙密诏、永历迁昆明、清军西南总攻、入缅、咒水之难、被引渡、处死。 Player Seat: 低行动力高象征性君主位。 相关事件 ../events/yongli burma terminal network 1659 1662.md：入缅、咒水、逼缅、押回昆明和死亡的终局总入口。 ../events/yongli flight to burma 1659.md：永历入缅。 ../events/yongli execution 1662.md：永历帝死亡。 来源 已核锚点：../source audit.md audit sm 0005，../source audit.md audit sm 0008，../source audit.md audit sm 0009，../source audit.md audit sm 0010，../source audit.md audit sm 0024，../source audit.md audit sm 0025，../source audit.md audit sm 0027，../source audit.md audit sm 0028，../source audit.md audit sm 0054，../source audit.md audit sm 0056，../source audit.md audit sm 0082，../source audit.md audit sm 0083，../source audit.md audit sm 0084，../source audit.md audit sm 0089，../source audit.md audit sm 0090，../source audit.md audit sm 0091，../source audit.md audit sm 0093，../source audit.md audit sm 0149，../source audit.md audit sm 0154，../source audit.md audit sm 0259，../source audit.md audit sm 0260，../source audit.md audit sm 0261，../source audit.md audit sm 0262，../source audit.md audit sm 0264，../source audit.md audit sm 0265，../source audit.md audit sm 0311，../source audit.md audit sm 0312。 顾诚：《南明史》，永历、西南、入缅、咒水之难和被杀相关章节，references/southern ming/books/gu cheng nanming shi guangming 2011.epub。 Wikisource《小腆纪年》《明季南略》，references/southern ming/primary sources/wikisource/。 待辨析 永历具体决策责任与马吉翔、李国泰、孙可望等人的责任边界。 1646 肇庆监国、梧州出奔、广州绍武并立和肇庆称帝的日级顺序需继续校。 1654 安龙密诏、1656 迁昆明、1658 西撤讨论中永历本人意志与朝臣/将领推动的边界需逐源辨析。 1651 南宁失守日、左江至安龙路线和安龙控制结构需继续地理/制度校勘。 入缅后敕书、玉玺、征南将军印核验和清方接收永历日序，需缅甸资料、清方资料和地方志继续互证。"
}
