{
  "id": "po-zhen-zi__events__yongli-guilin-wugang-1647",
  "title": "永历桂林、武冈流亡线 / Yongli Guilin-Wugang Flight, 1647",
  "sourcePath": "references/southern-ming/events/yongli-guilin-wugang-1647.md",
  "html": "<blockquote><p>Stable draft ID: <code>event.yongli_guilin_wugang_1647</code><br />Status: anchored seed dossier</p></blockquote>\n<h3>概要</h3>\n<p>1647 年初，广州绍武政权覆灭后，永历朝廷由肇庆退入广西。朱由榔正月到梧州，随后经平乐、桂林，最终转向全州、武冈；肇庆、梧州相继为清军取得，丁魁楚脱离行在后在出降链条中被杀。瞿式耜主张不可轻弃粤西，请留守桂林，和焦琏等在三月、五月两次抵住清方小股进攻。与此同时，刘承胤武冈兵力、王坤和马吉翔等近侍过滤共同推动永历离开桂林，使早期永历政权呈现“皇帝流亡、地方守土、防线和行在分离”的结构。</p>\n<h3>时间线</h3>\n<ul><li>1646 年十二月下旬至 1647 年正月：永历离开肇庆，正月初一前后到梧州；肇庆随后失守。</li><li>1647 年正月：永历由梧州经平乐趋桂林；梧州失守，曹烨降清，丁魁楚离散往岑溪并在出降链条中被杀。</li><li>1647 年正月至二月前后：永历抵桂林，瞿式耜整顿桂林府署行宫、守御和外部联络。</li><li>1647 年二月至四月：瞿式耜反对继续入楚/湖南，主张暂驻全州或守粤西；永历仍在王坤、马吉翔等近侍和刘承胤武冈兵力牵引下离桂。</li><li>1647 年三月：清方小股部队经平乐逼近并突入桂林文昌门，焦琏及时入城，配合瞿式耜击退来军。</li><li>1647 年五月：刘承胤援桂部队因饷需和主客不和发生哗变；二十五日前后清方再攻桂林，瞿式耜、焦琏、白贵等分守并击退。</li></ul>\n<h3>人物和地点</h3>\n<ul><li>Actors: 朱由榔、瞿式耜、焦琏、刘承胤、王坤、马吉翔、李成栋、丁魁楚、曹烨、陈邦傅、白贵、吴炳、方以智。</li><li>Places: 肇庆、梧州、岑溪、平乐、桂林、全州、武冈、阳朔。</li></ul>\n<h3>解释性笔记</h3>\n<p>这条线不是单一的“逃亡”事件。永历朝廷同时经历三种力量牵引：清军从广东入广西的追压，瞿式耜代表的桂林守土和制度修复，刘承胤等武冈/湖南方向兵力对皇帝安全的吸引。结果是皇帝名义权威、实际防线和地方军事实力分离：桂林能短暂稳住，但皇帝行在已向更强武力的保护者移动。</p>\n<p>桂林守御也需要分层。瞿式耜和焦琏确实稳定了桂林，但顾诚明确提醒 1647 年春夏进犯桂林的清军规模较小，李成栋主力回救广东；《小腆纪年》等材料中的战功叙事、斩获数字和“南渡以来”评价应作为记忆/评价层，不直接进入战役数值。</p>\n<h3>游戏数据线索</h3>\n<ul><li><code>Authority Fragmentation</code>: 皇帝行在、桂林守土和武冈兵权分离。</li><li><code>State Modifier Source</code>: 桂林防线稳定、行在流亡化、近侍过滤、地方武将挟驾风险。</li><li><code>Historical Candidate</code>: 永历是否留驻桂林/全州，是否接受瞿式耜守粤西方案。</li><li><code>AI Bias</code>: 瞿式耜高守土和制度修复倾向；刘承胤高兵权自重、高不可预测；王坤/马吉翔高近侍过滤。</li><li><code>Report Fact</code>: 梧州失守、桂林初建、武冈迁移、三月守城、五月兵变再守城应拆为多条报告事实。</li></ul>\n<h3>来源</h3>\n<ul><li><code>../source-audit.md#audit-sm-0014</code>：1647 年永历退往梧州、桂林与桂林守御的总框架。</li><li><code>../source-audit.md#audit-sm-0155</code>：正月永历至梧州、肇庆/梧州失守与丁魁楚离散。</li><li><code>../source-audit.md#audit-sm-0156</code>：永历抵桂林与桂林行在初建。</li><li><code>../source-audit.md#audit-sm-0157</code>：瞿式耜反对继续入楚、留守桂林与刘承胤武冈压力。</li><li><code>../source-audit.md#audit-sm-0158</code>：三月桂林第一次守御。</li><li><code>../source-audit.md#audit-sm-0159</code>：五月桂林再守御、兵变和战役规模异文。</li></ul>\n<h3>待辨析</h3>\n<ul><li>永历离开肇庆、抵梧州、抵平乐、抵桂林、去全州和驻武冈的日级换算。</li><li>丁魁楚在岑溪出降、被杀的执行者、日期、地点和财货数字。</li><li>刘承胤从迎驾、逐王坤到胁驾武冈、援桂兵变的阶段性责任。</li><li>三月和五月桂林守御的清方兵力、战果数字、战斗地点和叙事夸饰。</li><li>桂林府署行宫、全州/全阳驻跸建议和武冈行在的具体地理转换。</li></ul>",
  "plainText": "永历桂林、武冈流亡线 / Yongli Guilin Wugang Flight, 1647 Stable draft ID: event.yongli guilin wugang 1647 Status: anchored seed dossier 概要 1647 年初，广州绍武政权覆灭后，永历朝廷由肇庆退入广西。朱由榔正月到梧州，随后经平乐、桂林，最终转向全州、武冈；肇庆、梧州相继为清军取得，丁魁楚脱离行在后在出降链条中被杀。瞿式耜主张不可轻弃粤西，请留守桂林，和焦琏等在三月、五月两次抵住清方小股进攻。与此同时，刘承胤武冈兵力、王坤和马吉翔等近侍过滤共同推动永历离开桂林，使早期永历政权呈现“皇帝流亡、地方守土、防线和行在分离”的结构。 时间线 1646 年十二月下旬至 1647 年正月：永历离开肇庆，正月初一前后到梧州；肇庆随后失守。 1647 年正月：永历由梧州经平乐趋桂林；梧州失守，曹烨降清，丁魁楚离散往岑溪并在出降链条中被杀。 1647 年正月至二月前后：永历抵桂林，瞿式耜整顿桂林府署行宫、守御和外部联络。 1647 年二月至四月：瞿式耜反对继续入楚/湖南，主张暂驻全州或守粤西；永历仍在王坤、马吉翔等近侍和刘承胤武冈兵力牵引下离桂。 1647 年三月：清方小股部队经平乐逼近并突入桂林文昌门，焦琏及时入城，配合瞿式耜击退来军。 1647 年五月：刘承胤援桂部队因饷需和主客不和发生哗变；二十五日前后清方再攻桂林，瞿式耜、焦琏、白贵等分守并击退。 人物和地点 Actors: 朱由榔、瞿式耜、焦琏、刘承胤、王坤、马吉翔、李成栋、丁魁楚、曹烨、陈邦傅、白贵、吴炳、方以智。 Places: 肇庆、梧州、岑溪、平乐、桂林、全州、武冈、阳朔。 解释性笔记 这条线不是单一的“逃亡”事件。永历朝廷同时经历三种力量牵引：清军从广东入广西的追压，瞿式耜代表的桂林守土和制度修复，刘承胤等武冈/湖南方向兵力对皇帝安全的吸引。结果是皇帝名义权威、实际防线和地方军事实力分离：桂林能短暂稳住，但皇帝行在已向更强武力的保护者移动。 桂林守御也需要分层。瞿式耜和焦琏确实稳定了桂林，但顾诚明确提醒 1647 年春夏进犯桂林的清军规模较小，李成栋主力回救广东；《小腆纪年》等材料中的战功叙事、斩获数字和“南渡以来”评价应作为记忆/评价层，不直接进入战役数值。 游戏数据线索 Authority Fragmentation: 皇帝行在、桂林守土和武冈兵权分离。 State Modifier Source: 桂林防线稳定、行在流亡化、近侍过滤、地方武将挟驾风险。 Historical Candidate: 永历是否留驻桂林/全州，是否接受瞿式耜守粤西方案。 AI Bias: 瞿式耜高守土和制度修复倾向；刘承胤高兵权自重、高不可预测；王坤/马吉翔高近侍过滤。 Report Fact: 梧州失守、桂林初建、武冈迁移、三月守城、五月兵变再守城应拆为多条报告事实。 来源 ../source audit.md audit sm 0014：1647 年永历退往梧州、桂林与桂林守御的总框架。 ../source audit.md audit sm 0155：正月永历至梧州、肇庆/梧州失守与丁魁楚离散。 ../source audit.md audit sm 0156：永历抵桂林与桂林行在初建。 ../source audit.md audit sm 0157：瞿式耜反对继续入楚、留守桂林与刘承胤武冈压力。 ../source audit.md audit sm 0158：三月桂林第一次守御。 ../source audit.md audit sm 0159：五月桂林再守御、兵变和战役规模异文。 待辨析 永历离开肇庆、抵梧州、抵平乐、抵桂林、去全州和驻武冈的日级换算。 丁魁楚在岑溪出降、被杀的执行者、日期、地点和财货数字。 刘承胤从迎驾、逐王坤到胁驾武冈、援桂兵变的阶段性责任。 三月和五月桂林守御的清方兵力、战果数字、战斗地点和叙事夸饰。 桂林府署行宫、全州/全阳驻跸建议和武冈行在的具体地理转换。"
}
